pysolarcloud/__init__.py
pysolarcloud/control.py
pysolarcloud/plants.py
pysolarcloud-0.4.0.dist-info/licenses/LICENSE.txt
pysolarcloud-0.4.0.dist-info/METADATA
pysolarcloud-0.4.0.dist-info/WHEEL
pysolarcloud-0.4.0.dist-info/top_level.txt
pysolarcloud-0.4.0.dist-info/RECORD
