Metadata-Version: 2.4
Name: pysolarcloud
Version: 0.4.0
Summary: A library to interact with Sungrow's iSolarCloud API
Author-email: Tore Green <bugjam@e-dreams.dk>
License: MIT
Project-URL: Homepage, https://github.com/bugjam/pysolarcloud
Project-URL: Issues, https://github.com/bugjam/pysolarcloud/issues
Classifier: Programming Language :: Python :: 3
Classifier: Operating System :: OS Independent
Classifier: Framework :: AsyncIO
Classifier: Topic :: Home Automation
Requires-Python: >=3.7
License-File: LICENSE.txt
Requires-Dist: aiohttp
Provides-Extra: dev
Requires-Dist: pytest; extra == "dev"
Requires-Dist: pytest-asyncio; extra == "dev"
Dynamic: license-file
Dynamic: provides-extra
Dynamic: requires-dist
Dynamic: requires-python
